LICENSE.md
README.md
setup.py
downfile/__init__.py
downfile/utils.py
downfile.egg-info/PKG-INFO
downfile.egg-info/SOURCES.txt
downfile.egg-info/dependency_links.txt
downfile.egg-info/entry_points.txt
downfile.egg-info/requires.txt
downfile.egg-info/top_level.txt
downfile/formats/__init__.py
downfile/formats/format_datetime.py
downfile/formats/format_exception.py
downfile/formats/format_json.py
downfile/formats/format_numpy.py
downfile/formats/format_pandas.py